{
    "uuid": "954135da-1b22-4b84-a289-3451962d7390",
    "title": "Bapang Selisir SP",
    "composer": "",
    "instrumenttype": "SEMAR_PAGULINGAN",
    "positions": [
        "TROMPONG",
        "PEMADE_POLOS",
        "PEMADE_SANGSIH",
        "KANTILAN_POLOS",
        "KANTILAN_SANGSIH",
        "CALUNG",
        "JEGOGAN",
        "GONGS",
        "KEMPLI"
    ],
    "parts": {},
    "systems": [
        {
            "uuid": "162f28c2-6050-4d45-9123-ad03e82cce45",
            "id": 1,
            "index": 0,
            "execution": [
                {"type": "tempo", "seqId": 0, "tooltip": "tempo 100 BPM beat 1", "tooltipshort": "100 BPM", "isGradual": false, "toSection": 1, "toValue": 100.0}
            ],
            "staffs": {
                "TROMPONG": [{"notation": [".", ".", "o", "-"]}, {"notation": ["E", "u", "-", "-", "-"]}, {"notation": ["e", "-", "-", "-"]}, {"notation": ["a", "-", "-", "-"]}, {"notation": ["e", "-", "-", "-"]}, {"notation": ["o", "-", "-", "-"]}, {"notation": ["e", "-", "-", "u"]}, {"notation": ["a", "-", "u", "-"]}, {"notation": ["e", "-", "u", "u?"]}],
                "PEMADE_POLOS": [{"notation": [".", ".", ".", "."]}, {"notation": [".", ".", ".", "."]}, {"notation": [".", ".", ".", "."]}, {"notation": [".", ".", ".", "."]}, {"notation": [".", ".", ".", "."]}, {"notation": [".", ".", ".", "."]}, {"notation": [".", ".", ".", "."]}, {"notation": [".", ".", ".", "."]}, {"notation": [".", ".", ".", "."]}],
                "PEMADE_SANGSIH": [{"notation": [".", ".", ".", "."]}, {"notation": [".", ".", ".", "."]}, {"notation": [".", ".", ".", "."]}, {"notation": [".", ".", ".", "."]}, {"notation": [".", ".", ".", "."]}, {"notation": [".", ".", ".", "."]}, {"notation": [".", ".", ".", "."]}, {"notation": [".", ".", ".", "."]}, {"notation": [".", ".", ".", "."]}],
                "KANTILAN_POLOS": [{"notation": [".", ".", ".", "."]}, {"notation": [".", ".", ".", "."]}, {"notation": [".", ".", ".", "."]}, {"notation": [".", ".", ".", "."]}, {"notation": [".", ".", ".", "."]}, {"notation": [".", ".", ".", "."]}, {"notation": [".", ".", ".", "."]}, {"notation": [".", ".", ".", "."]}, {"notation": [".", ".", ".", "."]}],
                "KANTILAN_SANGSIH": [{"notation": [".", ".", ".", "."]}, {"notation": [".", ".", ".", "."]}, {"notation": [".", ".", ".", "."]}, {"notation": [".", ".", ".", "."]}, {"notation": [".", ".", ".", "."]}, {"notation": [".", ".", ".", "."]}, {"notation": [".", ".", ".", "."]}, {"notation": [".", ".", ".", "."]}, {"notation": [".", ".", ".", "."]}],
                "CALUNG": [{"notation": [".", ".", ".", "."]}, {"notation": [".", ".", ".", "."]}, {"notation": [".", ".", ".", "."]}, {"notation": [".", ".", ".", "."]}, {"notation": [".", ".", ".", "."]}, {"notation": [".", ".", ".", "."]}, {"notation": [".", ".", ".", "."]}, {"notation": [".", ".", ".", "."]}, {"notation": [".", ".", ".", "."]}],
                "JEGOGAN": [{"notation": [".", ".", ".", "."]}, {"notation": [".", ".", ".", "."]}, {"notation": [".", ".", ".", "."]}, {"notation": [".", ".", ".", "."]}, {"notation": [".", ".", ".", "."]}, {"notation": [".", ".", ".", "."]}, {"notation": [".", ".", ".", "."]}, {"notation": [".", ".", ".", "."]}, {"notation": [".", ".", ".", "."]}],
                "GONGS": [{"notation": [".", ".", ".", "."]}, {"notation": [".", ".", ".", "."]}, {"notation": [".", ".", ".", "."]}, {"notation": [".", ".", ".", "."]}, {"notation": [".", ".", ".", "."]}, {"notation": [".", ".", ".", "."]}, {"notation": [".", ".", ".", "."]}, {"notation": [".", ".", ".", "."]}, {"notation": [".", ".", ".", "."]}],
                "KEMPLI": [{"notation": ["-", "-", "-", "-"]}, {"notation": ["-", "-", "-", "-"]}, {"notation": ["-", "-", "-", "-"]}, {"notation": ["-", "-", "-", "-"]}, {"notation": ["-", "-", "-", "-"]}, {"notation": ["-", "-", "-", "-"]}, {"notation": ["-", "-", "-", "-"]}, {"notation": ["-", "-", "-", "-"]}, {"notation": ["-", "-", "-", "-"]}]
            },
            "colWidths": [4, 5, 4, 4, 4, 4, 4, 4, 4],
            "grouped": []
        },
        {
            "uuid": "8ea77f7e-cfdc-4977-bdec-400cddcc6e3f",
            "id": 2,
            "index": 1,
            "label": "Kawitan",
            "execution": [
                {"type": "loop", "seqId": 0, "tooltip": "play 3X", "tooltipshort": "3X", "count": 3},
                {"type": "dynamics", "seqId": 1, "tooltip": "dynamics mp beat 1", "tooltipshort": "mp", "isGradual": false, "toSection": 1, "toValue": 0.51, "toDynamics": "mp", "positions": ["PEMADE_POLOS", "PEMADE_SANGSIH", "KANTILAN_POLOS", "KANTILAN_SANGSIH"]},
                {"type": "dynamics", "seqId": 2, "tooltip": "dynamics mf beat 1", "tooltipshort": "mf", "isGradual": false, "toSection": 1, "toValue": 0.67, "toDynamics": "mf", "positions": ["TROMPONG"]}
            ],
            "staffs": {
                "TROMPONG": [{"notation": ["u", "-", "-", "-"]}, {"notation": ["e", "-", "-", "-"]}, {"notation": ["a", "-", "-", "-"]}, {"notation": ["e", "-", "-", "-"]}, {"notation": ["o", "-", "-", "-"]}, {"notation": ["e", "-", "-", "u"]}, {"notation": ["a", "-", "u", "-"]}, {"notation": ["e", "-", "u", "u?"]}],
                "PEMADE_POLOS": [{"notation": [".", "o", "e", "o"]}, {"notation": [".", "o", "e", "o"]}, {"notation": [".", "e", "o", "."]}, {"notation": ["e", "o", ".", "e"]}, {"notation": ["o", ".", "o", "e"]}, {"notation": [".", "o", "e", "."]}, {"notation": ["e", "o", ".", "e"]}, {"notation": ["o", ".", "o", "e"]}],
                "PEMADE_SANGSIH": [{"notation": ["u", "a", ".", "a"]}, {"notation": ["u", "a", ".", "a"]}, {"notation": ["u", ".", "a", "u"]}, {"notation": [".", "a", "u", "."]}, {"notation": ["a", "u", "a", "."]}, {"notation": ["u", "a", ".", "u"]}, {"notation": [".", "a", "u", "."]}, {"notation": ["a", "u", "a", "."]}],
                "KANTILAN_POLOS": [{"notation": [".", "o", "e", "o"]}, {"notation": [".", "o", "e", "o"]}, {"notation": [".", "e", "o", "."]}, {"notation": ["e", "o", ".", "e"]}, {"notation": ["o", ".", "o", "e"]}, {"notation": [".", "o", "e", "."]}, {"notation": ["e", "o", ".", "e"]}, {"notation": ["o", ".", "o", "e"]}],
                "KANTILAN_SANGSIH": [{"notation": ["u", "a", ".", "a"]}, {"notation": ["u", "a", ".", "a"]}, {"notation": ["u", ".", "a", "u"]}, {"notation": [".", "a", "u", "."]}, {"notation": ["a", "u", "a", "."]}, {"notation": ["u", "a", ".", "u"]}, {"notation": [".", "a", "u", "."]}, {"notation": ["a", "u", "a", "."]}],
                "CALUNG": [{"notation": ["u", "-", "-", "-"]}, {"notation": ["e", "-", "-", "-"]}, {"notation": ["a", "-", "-", "-"]}, {"notation": ["e", "-", "-", "-"]}, {"notation": ["o", "-", "-", "-"]}, {"notation": ["e", "-", "-", "-"]}, {"notation": ["a", "-", "-", "-"]}, {"notation": ["e", "-", "-", "-"]}],
                "JEGOGAN": [{"notation": ["u", "-", "-", "-"]}, {"notation": ["-", "-", "-", "-"]}, {"notation": ["-", "-", "-", "-"]}, {"notation": ["-", "-", "-", "-"]}, {"notation": ["o", "-", "-", "-"]}, {"notation": ["-", "-", "-", "-"]}, {"notation": ["-", "-", "-", "-"]}, {"notation": ["-", "-", "-", "-"]}],
                "GONGS": [{"notation": ["G", "-", "-", "-"]}, {"notation": ["-", "-", "-", "-"]}, {"notation": ["-", "-", "-", "-"]}, {"notation": ["-", "-", "-", "-"]}, {"notation": ["T", "-", "-", "-"]}, {"notation": ["-", "-", "-", "-"]}, {"notation": ["-", "-", "-", "-"]}, {"notation": ["-", "-", "-", "-"]}],
                "KEMPLI": [{"notation": ["x?", "-", "-", "-"]}, {"notation": ["x?", "-", "-", "-"]}, {"notation": ["x?", "-", "-", "-"]}, {"notation": ["x?", "-", "-", "-"]}, {"notation": ["x?", "-", "-", "-"]}, {"notation": ["x?", "-", "-", "-"]}, {"notation": ["x?", "-", "-", "-"]}, {"notation": ["x?", "-", "-", "-"]}]
            },
            "colWidths": [4, 4, 4, 4, 4, 4, 4, 4],
            "grouped": []
        },
        {
            "uuid": "f28ca73b-2643-46ee-a49d-a39d8dbbbb98",
            "id": 3,
            "index": 2,
            "execution": [
                {"type": "dynamics", "seqId": 0, "tooltip": "dynamics f beat 1", "tooltipshort": "f", "isGradual": false, "toSection": 1, "toValue": 0.83, "toDynamics": "f", "positions": ["PEMADE_POLOS", "PEMADE_SANGSIH", "KANTILAN_POLOS", "KANTILAN_SANGSIH", "TROMPONG"]}
            ],
            "staffs": {
                "TROMPONG": [{"notation": ["u", "-", "-", "-"]}, {"notation": ["e", "-", "-", "-"]}, {"notation": ["a", "-", "-", "-"]}, {"notation": ["e", "-", "-", "-"]}, {"notation": ["o", "-", "-", "-"]}, {"notation": ["e", "-", "-", "u"]}, {"notation": ["a", "-", "u", "-"]}, {"notation": ["e", "-", "u", "u?"]}],
                "PEMADE_POLOS": [{"notation": [".", "o", "e", "o"]}, {"notation": [".", "o", "e", "o"]}, {"notation": [".", "e", "o", "."]}, {"notation": ["e", "o", ".", "e"]}, {"notation": ["o", ".", "o", "e"]}, {"notation": [".", "o", "e", "."]}, {"notation": ["e", "o", ".", "e"]}, {"notation": ["o", ".", "o", "e"]}],
                "PEMADE_SANGSIH": [{"notation": ["u", "a", ".", "a"]}, {"notation": ["u", "a", ".", "a"]}, {"notation": ["u", ".", "a", "u"]}, {"notation": [".", "a", "u", "."]}, {"notation": ["a", "u", "a", "."]}, {"notation": ["u", "a", ".", "u"]}, {"notation": [".", "a", "u", "."]}, {"notation": ["a", "u", "a", "."]}],
                "KANTILAN_POLOS": [{"notation": [".", "o", "e", "o"]}, {"notation": [".", "o", "e", "o"]}, {"notation": [".", "e", "o", "."]}, {"notation": ["e", "o", ".", "e"]}, {"notation": ["o", ".", "o", "e"]}, {"notation": [".", "o", "e", "."]}, {"notation": ["e", "o", ".", "e"]}, {"notation": ["o", ".", "o", "e"]}],
                "KANTILAN_SANGSIH": [{"notation": ["u", "a", ".", "a"]}, {"notation": ["u", "a", ".", "a"]}, {"notation": ["u", ".", "a", "u"]}, {"notation": [".", "a", "u", "."]}, {"notation": ["a", "u", "a", "."]}, {"notation": ["u", "a", ".", "u"]}, {"notation": [".", "a", "u", "."]}, {"notation": ["a", "u", "a", "."]}],
                "CALUNG": [{"notation": ["u", "-", "-", "-"]}, {"notation": ["e", "-", "-", "-"]}, {"notation": ["a", "-", "-", "-"]}, {"notation": ["e", "-", "-", "-"]}, {"notation": ["o", "-", "-", "-"]}, {"notation": ["e", "-", "-", "-"]}, {"notation": ["a", "-", "-", "-"]}, {"notation": ["e", "-", "-", "-"]}],
                "JEGOGAN": [{"notation": ["u", "-", "-", "-"]}, {"notation": ["-", "-", "-", "-"]}, {"notation": ["-", "-", "-", "-"]}, {"notation": ["-", "-", "-", "-"]}, {"notation": ["o", "-", "-", "-"]}, {"notation": ["-", "-", "-", "-"]}, {"notation": ["-", "-", "-", "-"]}, {"notation": ["-", "-", "-", "-"]}],
                "GONGS": [{"notation": ["G", "-", "-", "-"]}, {"notation": ["-", "-", "-", "-"]}, {"notation": ["-", "-", "-", "-"]}, {"notation": ["-", "-", "-", "-"]}, {"notation": ["T", "-", "-", "-"]}, {"notation": ["-", "-", "-", "-"]}, {"notation": ["-", "-", "-", "-"]}, {"notation": ["-", "-", "-", "-"]}],
                "KEMPLI": [{"notation": ["x?", "-", "-", "-"]}, {"notation": ["x?", "-", "-", "-"]}, {"notation": ["x?", "-", "-", "-"]}, {"notation": ["x?", "-", "-", "-"]}, {"notation": ["x?", "-", "-", "-"]}, {"notation": ["x?", "-", "-", "-"]}, {"notation": ["x?", "-", "-", "-"]}, {"notation": ["x?", "-", "-", "-"]}]
            },
            "colWidths": [4, 4, 4, 4, 4, 4, 4, 4],
            "grouped": []
        },
        {
            "uuid": "fdcb2c98-32c2-44d7-a20e-a3d5ff2cb080",
            "id": 4,
            "index": 3,
            "execution": [
                {"type": "goto", "seqId": 0, "passes": [2, 4], "nthpass": false, "tooltip": "go to KAWITAN2 after passes 2 & 4", "tooltipshort": "KAWITAN2", "targetuuid": "232a1376-f9b7-4b27-bfd1-5839ffca5612", "targetname": "KAWITAN2"},
                {"type": "dynamics", "seqId": 1, "passes": [1, 3], "nthpass": false, "tooltip": "dynamics mp beat 5 on passes 1 & 3", "tooltipshort": "mp", "isGradual": false, "toSection": 5, "toValue": 0.51, "toDynamics": "mp", "positions": ["PEMADE_POLOS", "PEMADE_SANGSIH", "KANTILAN_POLOS", "KANTILAN_SANGSIH", "TROMPONG"]}
            ],
            "staffs": {
                "TROMPONG": [{"notation": ["u", "-", "-", "-"]}, {"notation": ["e", "-", "-", "-"]}, {"notation": ["a", "-", "-", "-"]}, {"notation": ["e", "-", "-", "-"]}, {"notation": ["o", "-", "-", "-"]}, {"notation": ["e", "-", "-", "-"]}, {"notation": ["a", "-", "-", "-"]}, {"notation": ["e", "-", "-", "-"]}],
                "PEMADE_POLOS": [{"notation": [".", "o", "e", "o"]}, {"notation": [".", "o", "e", "o"]}, {"notation": [".", "e", "o", "."]}, {"notation": ["e", "o", ".", "e"]}, {"notation": ["o", ".", "o", "-"]}, {"notation": ["E", "u", "-", "-", "-"]}, {"notation": ["-", "-", "-", "-"]}, {"notation": ["-", "-", "-", "-"]}],
                "PEMADE_SANGSIH": [{"notation": ["u", "a", ".", "a"]}, {"notation": ["u", "a", ".", "a"]}, {"notation": ["u", ".", "a", "u"]}, {"notation": [".", "a", "u", "."]}, {"notation": ["a", ".", "a", "-"]}, {"notation": ["S", "u", "-", "-", "-"]}, {"notation": ["-", "-", "-", "-"]}, {"notation": ["-", "-", "-", "-"]}],
                "KANTILAN_POLOS": [{"notation": [".", "o", "e", "o"]}, {"notation": [".", "o", "e", "o"]}, {"notation": [".", "e", "o", "."]}, {"notation": ["e", "o", ".", "e"]}, {"notation": ["o", ".", "o", "-"]}, {"notation": ["E", "u", "-", "-", "-"]}, {"notation": ["-", "-", "-", "-"]}, {"notation": ["-", "-", "-", "-"]}],
                "KANTILAN_SANGSIH": [{"notation": ["u", "a", ".", "a"]}, {"notation": ["u", "a", ".", "a"]}, {"notation": ["u", ".", "a", "u"]}, {"notation": [".", "a", "u", "."]}, {"notation": ["a", ".", "a", "-"]}, {"notation": ["S", "u", "-", "-", "-"]}, {"notation": ["-", "-", "-", "-"]}, {"notation": ["-", "-", "-", "-"]}],
                "CALUNG": [{"notation": ["u", "-", "-", "-"]}, {"notation": ["e", "-", "-", "-"]}, {"notation": ["a", "-", "-", "-"]}, {"notation": ["e", "-", "-", "-"]}, {"notation": ["o", "-", "-", "-"]}, {"notation": ["e", "-", "-", "-"]}, {"notation": ["a", "-", "-", "-"]}, {"notation": ["e", "-", "-", "-"]}],
                "JEGOGAN": [{"notation": ["u", "-", "-", "-"]}, {"notation": ["-", "-", "-", "-"]}, {"notation": ["-", "-", "-", "-"]}, {"notation": ["-", "-", "-", "-"]}, {"notation": ["o", "-", "-", "-"]}, {"notation": ["-", "-", "-", "-"]}, {"notation": ["-", "-", "-", "-"]}, {"notation": ["-", "-", "-", "-"]}],
                "GONGS": [{"notation": ["G", "-", "-", "-"]}, {"notation": ["-", "-", "-", "-"]}, {"notation": ["-", "-", "-", "-"]}, {"notation": ["-", "-", "-", "-"]}, {"notation": ["T", "-", "-", "-"]}, {"notation": ["-", "-", "-", "-"]}, {"notation": ["-", "-", "-", "-"]}, {"notation": ["-", "-", "-", "-"]}],
                "KEMPLI": [{"notation": ["x?", "-", "-", "-"]}, {"notation": ["x?", "-", "-", "-"]}, {"notation": ["x?", "-", "-", "-"]}, {"notation": ["x?", "-", "-", "-"]}, {"notation": ["x?", "-", "-", "-"]}, {"notation": ["x?", "-", "-", "-"]}, {"notation": ["x?", "-", "-", "-"]}, {"notation": ["x?", "-", "-", "-"]}]
            },
            "colWidths": [4, 4, 4, 4, 4, 5, 4, 4],
            "grouped": []
        },
        {
            "uuid": "00c1f930-0cb5-42a3-a687-798f206c3ea5",
            "id": 5,
            "index": 4,
            "execution": [
                {"type": "goto", "seqId": 0, "tooltip": "go to KAWITAN", "tooltipshort": "KAWITAN", "targetuuid": "8ea77f7e-cfdc-4977-bdec-400cddcc6e3f", "targetname": "KAWITAN"}
            ],
            "staffs": {
                "TROMPONG": [{"notation": ["u", "-", "-", "-"]}, {"notation": ["e", "-", "-", "-"]}, {"notation": ["a", "-", "-", "-"]}, {"notation": ["e", "-", "-", "-"]}, {"notation": ["o", "-", "-", "-"]}, {"notation": ["e", "-", "-", "-"]}, {"notation": ["a", "-", "-", "-"]}, {"notation": ["e", "-", "o", "e"]}],
                "PEMADE_POLOS": [{"notation": ["-", "-", "-", "-"]}, {"notation": ["-", "-", "-", "-"]}, {"notation": ["-", "-", "-", "-"]}, {"notation": ["-", "-", "-", "-"]}, {"notation": ["-", "-", "-", "-"]}, {"notation": ["-", "-", "-", "-"]}, {"notation": ["-", "-", "-", "-"]}, {"notation": [".", ".", ".", "."]}],
                "PEMADE_SANGSIH": [{"notation": ["-", "-", "-", "-"]}, {"notation": ["-", "-", "-", "-"]}, {"notation": ["-", "-", "-", "-"]}, {"notation": ["-", "-", "-", "-"]}, {"notation": ["-", "-", "-", "-"]}, {"notation": ["-", "-", "-", "-"]}, {"notation": ["-", "-", "-", "-"]}, {"notation": [".", ".", ".", "."]}],
                "KANTILAN_POLOS": [{"notation": ["-", "-", "-", "-"]}, {"notation": ["-", "-", "-", "-"]}, {"notation": ["-", "-", "-", "-"]}, {"notation": ["-", "-", "-", "-"]}, {"notation": ["-", "-", "-", "-"]}, {"notation": ["-", "-", "-", "-"]}, {"notation": ["-", "-", "-", "-"]}, {"notation": [".", ".", ".", "."]}],
                "KANTILAN_SANGSIH": [{"notation": ["-", "-", "-", "-"]}, {"notation": ["-", "-", "-", "-"]}, {"notation": ["-", "-", "-", "-"]}, {"notation": ["-", "-", "-", "-"]}, {"notation": ["-", "-", "-", "-"]}, {"notation": ["-", "-", "-", "-"]}, {"notation": ["-", "-", "-", "-"]}, {"notation": [".", ".", ".", "."]}],
                "CALUNG": [{"notation": ["u", "-", "-", "-"]}, {"notation": ["e", "-", "-", "-"]}, {"notation": ["a", "-", "-", "-"]}, {"notation": ["e", "-", "-", "-"]}, {"notation": ["o", "-", "-", "-"]}, {"notation": ["e", "-", "-", "-"]}, {"notation": ["a", "-", "-", "-"]}, {"notation": ["e", "-", "-", "-"]}],
                "JEGOGAN": [{"notation": ["u", "-", "-", "-"]}, {"notation": ["-", "-", "-", "-"]}, {"notation": ["-", "-", "-", "-"]}, {"notation": ["-", "-", "-", "-"]}, {"notation": ["o", "-", "-", "-"]}, {"notation": ["-", "-", "-", "-"]}, {"notation": ["-", "-", "-", "-"]}, {"notation": ["-", "-", "-", "-"]}],
                "GONGS": [{"notation": ["G", "-", "-", "-"]}, {"notation": ["-", "-", "-", "-"]}, {"notation": ["-", "-", "-", "-"]}, {"notation": ["-", "-", "-", "-"]}, {"notation": ["T", "-", "-", "-"]}, {"notation": ["-", "-", "-", "-"]}, {"notation": ["-", "-", "-", "-"]}, {"notation": ["-", "-", "-", "-"]}],
                "KEMPLI": [{"notation": ["x?", "-", "-", "-"]}, {"notation": ["x?", "-", "-", "-"]}, {"notation": ["x?", "-", "-", "-"]}, {"notation": ["x?", "-", "-", "-"]}, {"notation": ["x?", "-", "-", "-"]}, {"notation": ["x?", "-", "-", "-"]}, {"notation": ["x?", "-", "-", "-"]}, {"notation": ["x?", "-", "-", "-"]}]
            },
            "colWidths": [4, 4, 4, 4, 4, 4, 4, 4],
            "grouped": []
        },
        {
            "uuid": "232a1376-f9b7-4b27-bfd1-5839ffca5612",
            "id": 6,
            "index": 5,
            "label": "Kawitan2",
            "execution": [
                {"type": "dynamics", "seqId": 0, "tooltip": "dynamics f beat 1", "tooltipshort": "f", "isGradual": false, "toSection": 1, "toValue": 0.83, "toDynamics": "f", "positions": ["PEMADE_POLOS", "PEMADE_SANGSIH", "KANTILAN_POLOS", "KANTILAN_SANGSIH", "TROMPONG"]}
            ],
            "staffs": {
                "TROMPONG": [{"notation": ["u", "-", "-", "u"]}, {"notation": ["u", "-", "u", "-"]}, {"notation": ["u", "-", "a", "-"]}, {"notation": ["u", "-", "e", "-"]}, {"notation": ["o", "-", "-", "i"]}, {"notation": ["a,", "-", "i", "-"]}, {"notation": ["a,", "-", "-", "-"]}, {"notation": ["i", "-", "-", "-"]}],
                "PEMADE_POLOS": [{"notation": ["u", "-", "-", "u"]}, {"notation": ["u", "-", "u", "-"]}, {"notation": ["u", "-", "a", "-"]}, {"notation": ["u", "-", "e", "-"]}, {"notation": ["o", "-", "-", "i"]}, {"notation": ["a", "-", "i", "-"]}, {"notation": ["a", "-", "-", "-"]}, {"notation": ["i", "-", "-", "-"]}],
                "PEMADE_SANGSIH": [{"notation": ["u", "-", "-", "u"]}, {"notation": ["u", "-", "u", "-"]}, {"notation": ["u", "-", "a", "-"]}, {"notation": ["u", "-", "s", "-"]}, {"notation": ["a", "-", "-", "u"]}, {"notation": ["e", "-", "u", "-"]}, {"notation": ["e", "-", "-", "-"]}, {"notation": ["u", "-", "-", "-"]}],
                "KANTILAN_POLOS": [{"notation": ["u", "-", "-", "u"]}, {"notation": ["u", "-", "u", "-"]}, {"notation": ["u", "-", "a", "-"]}, {"notation": ["u", "-", "e", "-"]}, {"notation": ["o", "-", "-", "i"]}, {"notation": ["a", "-", "i", "-"]}, {"notation": ["a", "-", "-", "-"]}, {"notation": ["i", "-", "-", "-"]}],
                "KANTILAN_SANGSIH": [{"notation": ["u", "-", "-", "u"]}, {"notation": ["u", "-", "u", "-"]}, {"notation": ["u", "-", "a", "-"]}, {"notation": ["u", "-", "s", "-"]}, {"notation": ["a", "-", "-", "u"]}, {"notation": ["e", "-", "u", "-"]}, {"notation": ["e", "-", "-", "-"]}, {"notation": ["u", "-", "-", "-"]}],
                "CALUNG": [{"notation": ["u", "-", "-", "u"]}, {"notation": ["u", "-", "u", "-"]}, {"notation": ["u", "-", "a", "-"]}, {"notation": ["u", "-", "e", "-"]}, {"notation": ["o", "-", "-", "i"]}, {"notation": ["a", "-", "i", "-"]}, {"notation": ["a", "-", "-", "-"]}, {"notation": ["i", "-", "-", "-"]}],
                "JEGOGAN": [{"notation": ["u", "-", "-", "-"]}, {"notation": ["-", "-", "-", "-"]}, {"notation": ["-", "-", "-", "-"]}, {"notation": ["-", "-", "-", "-"]}, {"notation": ["o", "-", "-", "-"]}, {"notation": ["-", "-", "-", "-"]}, {"notation": ["-", "-", "-", "-"]}, {"notation": ["-", "-", "-", "-"]}],
                "GONGS": [{"notation": ["G", "-", "-", "-"]}, {"notation": ["-", "-", "-", "-"]}, {"notation": ["-", "-", "-", "-"]}, {"notation": ["-", "-", "-", "-"]}, {"notation": ["T", "-", "-", "-"]}, {"notation": ["-", "-", "-", "-"]}, {"notation": ["-", "-", "-", "-"]}, {"notation": ["-", "-", "-", "-"]}],
                "KEMPLI": [{"notation": ["x?", "-", "-", "-"]}, {"notation": ["x?", "-", "-", "-"]}, {"notation": ["x?", "-", "-", "-"]}, {"notation": ["x?", "-", "-", "-"]}, {"notation": ["x?", "-", "-", "-"]}, {"notation": ["x?", "-", "-", "-"]}, {"notation": ["x?", "-", "-", "-"]}, {"notation": ["x?", "-", "-", "-"]}]
            },
            "colWidths": [4, 4, 4, 4, 4, 4, 4, 4],
            "grouped": []
        },
        {
            "uuid": "1077b61f-ae56-4198-ac19-2f4d8b9abbc9",
            "id": 7,
            "index": 6,
            "execution": [],
            "staffs": {
                "TROMPONG": [{"notation": ["o", "-", "-", "o"]}, {"notation": ["o", "-", "o", "-"]}, {"notation": ["o", "-", "e", "-"]}, {"notation": ["o", "-", "i", "-"]}, {"notation": ["a,", "-", "i", "o"]}, {"notation": ["e", "-", "o", "-"]}, {"notation": ["e", "-", "-", "-"]}, {"notation": ["u", "-", "-", "-"]}],
                "PEMADE_POLOS": [{"notation": ["o", "-", "-", "o"]}, {"notation": ["o", "-", "o", "-"]}, {"notation": ["o", "-", "e", "-"]}, {"notation": ["o", "-", "i", "-"]}, {"notation": ["a", "-", "i", "o"]}, {"notation": ["e", "-", "o", "-"]}, {"notation": ["e", "-", "-", "-"]}, {"notation": ["u", "-", "-", "-"]}],
                "PEMADE_SANGSIH": [{"notation": ["a", "-", "-", "a"]}, {"notation": ["a", "-", "a", "-"]}, {"notation": ["a", "-", "s", "-"]}, {"notation": ["a", "-", "u", "-"]}, {"notation": ["e", "-", "u", "a"]}, {"notation": ["s", "-", "a", "-"]}, {"notation": ["s", "-", "-", "-"]}, {"notation": ["u", "-", "-", "-"]}],
                "KANTILAN_POLOS": [{"notation": ["o", "-", "-", "o"]}, {"notation": ["o", "-", "o", "-"]}, {"notation": ["o", "-", "e", "-"]}, {"notation": ["o", "-", "i", "-"]}, {"notation": ["a", "-", "i", "o"]}, {"notation": ["e", "-", "o", "-"]}, {"notation": ["e", "-", "-", "-"]}, {"notation": ["u", "-", "-", "-"]}],
                "KANTILAN_SANGSIH": [{"notation": ["a", "-", "-", "a"]}, {"notation": ["a", "-", "a", "-"]}, {"notation": ["a", "-", "s", "-"]}, {"notation": ["a", "-", "u", "-"]}, {"notation": ["e", "-", "u", "a"]}, {"notation": ["s", "-", "a", "-"]}, {"notation": ["s", "-", "-", "-"]}, {"notation": ["u", "-", "-", "-"]}],
                "CALUNG": [{"notation": ["o", "-", "-", "o"]}, {"notation": ["o", "-", "o", "-"]}, {"notation": ["o", "-", "e", "-"]}, {"notation": ["o", "-", "i", "-"]}, {"notation": ["a", "-", "i", "o"]}, {"notation": ["e", "-", "o", "-"]}, {"notation": ["e", "-", "-", "-"]}, {"notation": ["u", "-", "-", "-"]}],
                "JEGOGAN": [{"notation": ["o", "-", "-", "-"]}, {"notation": ["-", "-", "-", "-"]}, {"notation": ["-", "-", "-", "-"]}, {"notation": ["-", "-", "-", "-"]}, {"notation": ["o", "-", "-", "-"]}, {"notation": ["-", "-", "-", "-"]}, {"notation": ["-", "-", "-", "-"]}, {"notation": ["-", "-", "-", "-"]}],
                "GONGS": [{"notation": ["G", "-", "-", "-"]}, {"notation": ["-", "-", "-", "-"]}, {"notation": ["-", "-", "-", "-"]}, {"notation": ["-", "-", "-", "-"]}, {"notation": ["T", "-", "-", "-"]}, {"notation": ["-", "-", "-", "-"]}, {"notation": ["-", "-", "-", "-"]}, {"notation": ["-", "-", "-", "-"]}],
                "KEMPLI": [{"notation": ["x?", "-", "-", "-"]}, {"notation": ["x?", "-", "-", "-"]}, {"notation": ["x?", "-", "-", "-"]}, {"notation": ["x?", "-", "-", "-"]}, {"notation": ["x?", "-", "-", "-"]}, {"notation": ["x?", "-", "-", "-"]}, {"notation": ["x?", "-", "-", "-"]}, {"notation": ["x?", "-", "-", "-"]}]
            },
            "colWidths": [4, 4, 4, 4, 4, 4, 4, 4],
            "grouped": []
        },
        {
            "uuid": "5c50f8a9-0e67-41bc-a6de-5f8f9f5b4ea4",
            "id": 8,
            "index": 7,
            "execution": [],
            "staffs": {
                "TROMPONG": [{"notation": ["e", "-", "-", "e"]}, {"notation": ["e", "-", "e", "-"]}, {"notation": ["e", "-", "a", "-"]}, {"notation": ["u", "-", "e", "-"]}, {"notation": ["o", "-", "-", "e"]}, {"notation": ["u", "-", "e", "-"]}, {"notation": ["u", "-", "-", "-"]}, {"notation": ["a", "-", "-", "-"]}],
                "PEMADE_POLOS": [{"notation": ["e", "-", "-", "e"]}, {"notation": ["e", "-", "e", "-"]}, {"notation": ["e", "-", "a", "-"]}, {"notation": ["u", "-", "e", "-"]}, {"notation": ["o", "-", "-", "e"]}, {"notation": ["u", "-", "e", "-"]}, {"notation": ["u", "-", "-", "-"]}, {"notation": ["a", "-", "-", "-"]}],
                "PEMADE_SANGSIH": [{"notation": ["s", "-", "-", "s"]}, {"notation": ["s", "-", "s", "-"]}, {"notation": ["s", "-", "a", "-"]}, {"notation": ["u", "-", "s", "-"]}, {"notation": ["a", "-", "-", "s"]}, {"notation": ["u", "-", "s", "-"]}, {"notation": ["u", "-", "-", "-"]}, {"notation": ["a", "-", "-", "-"]}],
                "KANTILAN_POLOS": [{"notation": ["e", "-", "-", "e"]}, {"notation": ["e", "-", "e", "-"]}, {"notation": ["e", "-", "a", "-"]}, {"notation": ["u", "-", "e", "-"]}, {"notation": ["o", "-", "-", "e"]}, {"notation": ["u", "-", "e", "-"]}, {"notation": ["u", "-", "-", "-"]}, {"notation": ["a", "-", "-", "-"]}],
                "KANTILAN_SANGSIH": [{"notation": ["s", "-", "-", "s"]}, {"notation": ["s", "-", "s", "-"]}, {"notation": ["s", "-", "a", "-"]}, {"notation": ["u", "-", "s", "-"]}, {"notation": ["a", "-", "-", "s"]}, {"notation": ["u", "-", "s", "-"]}, {"notation": ["u", "-", "-", "-"]}, {"notation": ["a", "-", "-", "-"]}],
                "CALUNG": [{"notation": ["e", "-", "-", "e"]}, {"notation": ["e", "-", "e", "-"]}, {"notation": ["e", "-", "a", "-"]}, {"notation": ["u", "-", "e", "-"]}, {"notation": ["o", "-", "-", "e"]}, {"notation": ["u", "-", "e", "-"]}, {"notation": ["u", "-", "-", "-"]}, {"notation": ["a", "-", "-", "-"]}],
                "JEGOGAN": [{"notation": ["e", "-", "-", "-"]}, {"notation": ["-", "-", "-", "-"]}, {"notation": ["-", "-", "-", "-"]}, {"notation": ["-", "-", "-", "-"]}, {"notation": ["o", "-", "-", "-"]}, {"notation": ["-", "-", "-", "-"]}, {"notation": ["-", "-", "-", "-"]}, {"notation": ["-", "-", "-", "-"]}],
                "GONGS": [{"notation": ["G", "-", "-", "-"]}, {"notation": ["-", "-", "-", "-"]}, {"notation": ["-", "-", "-", "-"]}, {"notation": ["-", "-", "-", "-"]}, {"notation": ["T", "-", "-", "-"]}, {"notation": ["-", "-", "-", "-"]}, {"notation": ["-", "-", "-", "-"]}, {"notation": ["-", "-", "-", "-"]}],
                "KEMPLI": [{"notation": ["x?", "-", "-", "-"]}, {"notation": ["x?", "-", "-", "-"]}, {"notation": ["x?", "-", "-", "-"]}, {"notation": ["x?", "-", "-", "-"]}, {"notation": ["x?", "-", "-", "-"]}, {"notation": ["x?", "-", "-", "-"]}, {"notation": ["x?", "-", "-", "-"]}, {"notation": ["x?", "-", "-", "-"]}]
            },
            "colWidths": [4, 4, 4, 4, 4, 4, 4, 4],
            "grouped": []
        },
        {
            "uuid": "31ddcdaa-497e-4d95-8b70-de6fc6213056",
            "id": 9,
            "index": 8,
            "execution": [
                {"type": "goto", "seqId": 0, "passes": [1], "nthpass": false, "tooltip": "go to KAWITAN after pass 1", "tooltipshort": "KAWITAN", "targetuuid": "8ea77f7e-cfdc-4977-bdec-400cddcc6e3f", "targetname": "KAWITAN"}
            ],
            "staffs": {
                "TROMPONG": [{"notation": ["u", "-", "-", "u"]}, {"notation": ["u", "-", "u", "-"]}, {"notation": ["u", "-", "a", "-"]}, {"notation": ["u", "-", "e", "-"]}, {"notation": ["o", ".", "o", "-"]}, {"notation": ["E", "u", "-", "-", "-"]}, {"notation": ["-", "-", "-", "-"]}, {"notation": ["-", "-", "-", "-"]}],
                "PEMADE_POLOS": [{"notation": ["u", "-", "-", "u"]}, {"notation": ["u", "-", "u", "-"]}, {"notation": ["u", "-", "a", "-"]}, {"notation": ["u", "-", "e", "-"]}, {"notation": ["o", ".", "o", "-"]}, {"notation": ["E", "u", "-", "-", "-"]}, {"notation": ["-", "-", "-", "-"]}, {"notation": ["-", "-", "-", "-"]}],
                "PEMADE_SANGSIH": [{"notation": ["u", "-", "-", "u"]}, {"notation": ["u", "-", "u", "-"]}, {"notation": ["u", "-", "a", "-"]}, {"notation": ["u", "-", "s", "-"]}, {"notation": ["a", ".", "a", "-"]}, {"notation": ["S", "u", "-", "-", "-"]}, {"notation": ["-", "-", "-", "-"]}, {"notation": ["-", "-", "-", "-"]}],
                "KANTILAN_POLOS": [{"notation": ["u", "-", "-", "u"]}, {"notation": ["u", "-", "u", "-"]}, {"notation": ["u", "-", "a", "-"]}, {"notation": ["u", "-", "e", "-"]}, {"notation": ["o", ".", "o", "-"]}, {"notation": ["E", "u", "-", "-", "-"]}, {"notation": ["-", "-", "-", "-"]}, {"notation": ["-", "-", "-", "-"]}],
                "KANTILAN_SANGSIH": [{"notation": ["u", "-", "-", "u"]}, {"notation": ["u", "-", "u", "-"]}, {"notation": ["u", "-", "a", "-"]}, {"notation": ["u", "-", "s", "-"]}, {"notation": ["a", ".", "a", "-"]}, {"notation": ["S", "u", "-", "-", "-"]}, {"notation": ["-", "-", "-", "-"]}, {"notation": ["-", "-", "-", "-"]}],
                "CALUNG": [{"notation": ["u", "-", "-", "u"]}, {"notation": ["u", "-", "u", "-"]}, {"notation": ["u", "-", "a", "-"]}, {"notation": ["u", "-", "e", "-"]}, {"notation": ["o", ".", "e", "-"]}, {"notation": ["u", "-", "-", "-"]}, {"notation": ["-", "-", "-", "-"]}, {"notation": ["-", "-", "-", "-"]}],
                "JEGOGAN": [{"notation": ["u", "-", "-", "-"]}, {"notation": ["-", "-", "-", "-"]}, {"notation": ["-", "-", "-", "-"]}, {"notation": ["-", "-", "-", "-"]}, {"notation": ["o", "-", "-", "-"]}, {"notation": ["-", "-", "-", "-"]}, {"notation": ["-", "-", "-", "-"]}, {"notation": ["-", "-", "-", "-"]}],
                "GONGS": [{"notation": ["G", "-", "-", "-"]}, {"notation": ["-", "-", "-", "-"]}, {"notation": ["-", "-", "-", "-"]}, {"notation": ["-", "-", "-", "-"]}, {"notation": ["T", "-", "-", "-"]}, {"notation": ["-", "-", "-", "-"]}, {"notation": ["-", "-", "-", "-"]}, {"notation": ["-", "-", "-", "-"]}],
                "KEMPLI": [{"notation": ["x?", "-", "-", "-"]}, {"notation": ["x?", "-", "-", "-"]}, {"notation": ["x?", "-", "-", "-"]}, {"notation": ["x?", "-", "-", "-"]}, {"notation": ["x?", "-", "-", "-"]}, {"notation": ["x?", "-", "-", "-"]}, {"notation": ["x?", "-", "-", "-"]}, {"notation": ["x?", "-", "-", "-"]}]
            },
            "colWidths": [4, 4, 4, 4, 4, 5, 4, 4],
            "grouped": []
        },
        {
            "uuid": "af2170f2-26b8-4289-a44f-b78167c7d56b",
            "id": 10,
            "index": 9,
            "execution": [
                {"type": "loop", "seqId": 0, "tooltip": "play 2X", "tooltipshort": "2X", "count": 2},
                {"type": "dynamics", "seqId": 1, "tooltip": "dynamics mp beat 1", "tooltipshort": "mp", "isGradual": false, "toSection": 1, "toValue": 0.51, "toDynamics": "mp", "positions": ["PEMADE_POLOS", "PEMADE_SANGSIH", "KANTILAN_POLOS", "KANTILAN_SANGSIH"]},
                {"type": "dynamics", "seqId": 2, "tooltip": "dynamics mf beat 1", "tooltipshort": "mf", "isGradual": false, "toSection": 1, "toValue": 0.67, "toDynamics": "mf", "positions": ["TROMPONG"]},
                {"type": "tempo", "seqId": 3, "tooltip": "tempo 60 BPM beat 1 on 2nd iteration", "tooltipshort": "60 BPM", "iterations": [2], "isGradual": false, "toSection": 1, "toValue": 60.0}
            ],
            "staffs": {
                "TROMPONG": [{"notation": ["u", "-", "-", "-"]}, {"notation": ["e", "-", "-", "-"]}, {"notation": ["a", "-", "-", "-"]}, {"notation": ["e", "-", "-", "-"]}, {"notation": ["o", "-", "-", "-"]}, {"notation": ["e", "-", "-", "u"]}, {"notation": ["a", "-", "u", "-"]}, {"notation": ["e", "-", "-", "o"]}],
                "PEMADE_POLOS": [{"notation": [".", "o", "e", "o"]}, {"notation": [".", "o", "e", "o"]}, {"notation": [".", "e", "o", "."]}, {"notation": ["e", "o", ".", "e"]}, {"notation": ["o", ".", "o", "e"]}, {"notation": [".", "o", "e", "."]}, {"notation": ["e", "o", ".", "e"]}, {"notation": ["o", ".", "o", "e"]}],
                "PEMADE_SANGSIH": [{"notation": ["u", "a", ".", "a"]}, {"notation": ["u", "a", ".", "a"]}, {"notation": ["u", ".", "a", "u"]}, {"notation": [".", "a", "u", "."]}, {"notation": ["a", "u", "a", "."]}, {"notation": ["u", "a", ".", "u"]}, {"notation": [".", "a", "u", "."]}, {"notation": ["a", "u", "a", "."]}],
                "KANTILAN_POLOS": [{"notation": [".", "o", "e", "o"]}, {"notation": [".", "o", "e", "o"]}, {"notation": [".", "e", "o", "."]}, {"notation": ["e", "o", ".", "e"]}, {"notation": ["o", ".", "o", "e"]}, {"notation": [".", "o", "e", "."]}, {"notation": ["e", "o", ".", "e"]}, {"notation": ["o", ".", "o", "e"]}],
                "KANTILAN_SANGSIH": [{"notation": ["u", "a", ".", "a"]}, {"notation": ["u", "a", ".", "a"]}, {"notation": ["u", ".", "a", "u"]}, {"notation": [".", "a", "u", "."]}, {"notation": ["a", "u", "a", "."]}, {"notation": ["u", "a", ".", "u"]}, {"notation": [".", "a", "u", "."]}, {"notation": ["a", "u", "a", "."]}],
                "CALUNG": [{"notation": ["u", "-", "-", "-"]}, {"notation": ["e", "-", "-", "-"]}, {"notation": ["a", "-", "-", "-"]}, {"notation": ["e", "-", "-", "-"]}, {"notation": ["o", "-", "-", "-"]}, {"notation": ["e", "-", "-", "-"]}, {"notation": ["a", "-", "-", "-"]}, {"notation": ["e", "-", "-", "-"]}],
                "JEGOGAN": [{"notation": ["u", "-", "-", "-"]}, {"notation": ["-", "-", "-", "-"]}, {"notation": ["a", "-", "-", "-"]}, {"notation": ["-", "-", "-", "-"]}, {"notation": ["o", "-", "-", "-"]}, {"notation": ["-", "-", "-", "-"]}, {"notation": ["a", "-", "-", "-"]}, {"notation": ["-", "-", "-", "-"]}],
                "GONGS": [{"notation": ["G", "-", "-", "-"]}, {"notation": ["-", "-", "-", "-"]}, {"notation": ["-", "-", "-", "-"]}, {"notation": ["-", "-", "-", "-"]}, {"notation": ["T", "-", "-", "-"]}, {"notation": ["-", "-", "-", "-"]}, {"notation": ["-", "-", "-", "-"]}, {"notation": ["-", "-", "-", "-"]}],
                "KEMPLI": [{"notation": ["x?", "-", "-", "-"]}, {"notation": ["x?", "-", "-", "-"]}, {"notation": ["x?", "-", "-", "-"]}, {"notation": ["x?", "-", "-", "-"]}, {"notation": ["x?", "-", "-", "-"]}, {"notation": ["x?", "-", "-", "-"]}, {"notation": ["x?", "-", "-", "-"]}, {"notation": ["x?", "-", "-", "-"]}]
            },
            "colWidths": [4, 4, 4, 4, 4, 4, 4, 4],
            "grouped": []
        },
        {
            "uuid": "4911845f-45de-47d9-90c7-20348e63808d",
            "id": 11,
            "index": 10,
            "execution": [],
            "staffs": {
                "TROMPONG": [{"notation": ["E", "u"]}],
                "PEMADE_POLOS": [{"notation": ["u"]}],
                "PEMADE_SANGSIH": [{"notation": ["u"]}],
                "KANTILAN_POLOS": [{"notation": ["u"]}],
                "KANTILAN_SANGSIH": [{"notation": ["u"]}],
                "CALUNG": [{"notation": ["u"]}],
                "JEGOGAN": [{"notation": ["u"]}],
                "GONGS": [{"notation": ["G"]}],
                "KEMPLI": [{"notation": ["x?"]}]
            },
            "colWidths": [2],
            "grouped": []
        }
    ]
}